tn_radio/__init__.py
tn_radio-0.1.11.dist-info/LICENSE
tn_radio-0.1.11.dist-info/METADATA
tn_radio-0.1.11.dist-info/WHEEL
tn_radio-0.1.11.dist-info/top_level.txt
tn_radio-0.1.11.dist-info/RECORD
