Metadata-Version: 2.1
Name: tn-radio
Version: 0.1.11
Summary: Tamil Nadu Local Online Fm Station
Home-page: https://github.com/THAVASIGTI/tn_radio.git
Author: THAVASIGTI
Author-email: ganeshanthavasigti1032000@gmail.com
License: UNKNOWN
Platform: UNKNOWN
Classifier: Programming Language :: Python :: 3
Classifier: License :: OSI Approved :: MIT License
Classifier: Operating System :: OS Independent
Requires-Python: >=3
License-File: LICENSE
Requires-Dist: python-vlc
